ai/backend/manager/VERSION
ai/backend/manager/__init__.py
ai/backend/manager/agent_cache.py
ai/backend/manager/config_legacy.py
ai/backend/manager/defs.py
ai/backend/manager/exceptions.py
ai/backend/manager/idle.py
ai/backend/manager/openapi.py
ai/backend/manager/pglock.py
ai/backend/manager/py.typed
ai/backend/manager/registry.py
ai/backend/manager/server.py
ai/backend/manager/server_bgtask_ctx.py
ai/backend/manager/server_gql_ctx.py
ai/backend/manager/types.py
ai/backend/manager/utils.py
ai/backend/manager/actions/__init__.py
ai/backend/manager/actions/types.py
ai/backend/manager/actions/action/__init__.py
ai/backend/manager/actions/action/base.py
ai/backend/manager/actions/action/batch.py
ai/backend/manager/actions/action/scope.py
ai/backend/manager/actions/action/single_entity.py
ai/backend/manager/actions/action/types.py
ai/backend/manager/actions/monitors/__init__.py
ai/backend/manager/actions/monitors/audit_log.py
ai/backend/manager/actions/monitors/monitor.py
ai/backend/manager/actions/monitors/prometheus.py
ai/backend/manager/actions/monitors/reporter.py
ai/backend/manager/actions/processor/__init__.py
ai/backend/manager/actions/processor/base.py
ai/backend/manager/actions/processor/batch.py
ai/backend/manager/actions/processor/scope.py
ai/backend/manager/actions/processor/single_entity.py
ai/backend/manager/actions/validator/__init__.py
ai/backend/manager/actions/validator/base.py
ai/backend/manager/actions/validator/batch.py
ai/backend/manager/actions/validator/scope.py
ai/backend/manager/actions/validator/single_entity.py
ai/backend/manager/actions/validators/__init__.py
ai/backend/manager/actions/validators/auth_validator.py
ai/backend/manager/actions/validators/rbac/__init__.py
ai/backend/manager/actions/validators/rbac/batch.py
ai/backend/manager/actions/validators/rbac/scope.py
ai/backend/manager/actions/validators/rbac/single_entity.py
ai/backend/manager/api/__init__.py
ai/backend/manager/api/acl.py
ai/backend/manager/api/adapter.py
backend_ai_manager-26.1.0.dist-info/METADATA
backend_ai_manager-26.1.0.dist-info/WHEEL
backend_ai_manager-26.1.0.dist-info/entry_points.txt
backend_ai_manager-26.1.0.dist-info/namespace_packages.txt
backend_ai_manager-26.1.0.dist-info/top_level.txt
backend_ai_manager-26.1.0.dist-info/RECORD
