Metadata-Version: 2.4
Name: backend.ai-manager
Version: 26.1.0
Summary: Backend.AI Manager
Home-page: https://github.com/lablup/backend.ai
Author: Lablup Inc. and contributors
License: LGPLv3
Project-URL: Documentation, https://docs.backend.ai/
Project-URL: Source, https://github.com/lablup/backend.ai
Classifier: Intended Audience :: Developers
Classifier: Operating System :: MacOS :: MacOS X
Classifier: Operating System :: POSIX :: Linux
Classifier: Programming Language :: Python
Classifier: Programming Language :: Python :: 3
Classifier: Environment :: No Input/Output (Daemon)
Classifier: Topic :: Scientific/Engineering
Classifier: Topic :: Software Development
Classifier: Development Status :: 5 - Production/Stable
Classifier: Programming Language :: Python :: 3.13
Classifier: License :: OSI Approved :: GNU Lesser General Public License v3 or later (LGPLv3+)
Requires-Python: >=3.13,<3.14
Requires-Dist: Jinja2~=3.1.6
Requires-Dist: PyJWT~=2.10.1
Requires-Dist: PyYAML~=6.0
Requires-Dist: SQLAlchemy[postgresql_asyncpg]~=2.0.45
Requires-Dist: aiodataloader~=0.4.2
Requires-Dist: aiodocker==0.24.0
Requires-Dist: aiofiles~=24.1.0
Requires-Dist: aiohttp_cors~=0.8.1
Requires-Dist: aiohttp_sse>=2.2
Requires-Dist: aiohttp~=3.13.3
Requires-Dist: aiomonitor~=0.7.0
Requires-Dist: aiotools~=2.2.3
Requires-Dist: alembic~=1.13.2
Requires-Dist: async_timeout~=4.0
Requires-Dist: attrs>=25.3
Requires-Dist: backend.ai-cli==26.1.0
Requires-Dist: backend.ai-common==26.1.0
Requires-Dist: backend.ai-logging==26.1.0
Requires-Dist: backend.ai-plugin==26.1.0
Requires-Dist: bcrypt~=4.2.0
Requires-Dist: boto3~=1.35
Requires-Dist: callosum~=1.0.3
Requires-Dist: click~=8.1.7
Requires-Dist: cryptography>=44.0.2
Requires-Dist: etcd-client-py~=0.5.1
Requires-Dist: graphene-federation~=3.2.0
Requires-Dist: graphene~=3.3.0
Requires-Dist: graphql-core~=3.2.6
Requires-Dist: graphql-relay~=3.2.0
Requires-Dist: lark~=1.1.5
Requires-Dist: more-itertools~=10.5.0
Requires-Dist: msgpack~=1.1.0
Requires-Dist: multidict~=6.6.4
Requires-Dist: prometheus-client~=0.21.1
Requires-Dist: pydantic[email]~=2.11.3
Requires-Dist: python-dateutil>=2.9
Requires-Dist: pyzmq~=26.4
Requires-Dist: redis[hiredis]~=7.1.0
Requires-Dist: ruamel.yaml~=0.18.10
Requires-Dist: setproctitle~=1.3.5
Requires-Dist: strawberry-graphql~=0.278.0
Requires-Dist: tabulate~=0.8.9
Requires-Dist: tenacity>=9.0
Requires-Dist: tomli~=2.0.1
Requires-Dist: trafaret~=2.1
Requires-Dist: typeguard~=4.3
Requires-Dist: types-Jinja2
Requires-Dist: types-PyYAML
Requires-Dist: types-aiofiles
Requires-Dist: types-python-dateutil
Requires-Dist: types-redis
Requires-Dist: types-six
Requires-Dist: types-tabulate
Requires-Dist: typing_extensions~=4.11
Requires-Dist: uvloop~=0.22.1; sys_platform != "Windows"
Requires-Dist: valkey-glide~=2.2.2
Requires-Dist: yarl~=1.19.0
Dynamic: author
Dynamic: classifier
Dynamic: description
Dynamic: description-content-type
Dynamic: home-page
Dynamic: license
Dynamic: project-url
Dynamic: requires-dist
Dynamic: requires-python
Dynamic: summary
